custom_test_package_that_does_nothing/__init__.py
custom_test_package_that_does_nothing-0.2.1.dist-info/LICENSE
custom_test_package_that_does_nothing-0.2.1.dist-info/METADATA
custom_test_package_that_does_nothing-0.2.1.dist-info/WHEEL
custom_test_package_that_does_nothing-0.2.1.dist-info/top_level.txt
custom_test_package_that_does_nothing-0.2.1.dist-info/RECORD
