Metadata-Version: 2.1
Name: custom-test-package-that-does-nothing
Version: 0.2.1
Summary: A python library that does nothing
Home-page: https://github.com/makarandh/do-nothing
Author: Mak
Author-email: 38956972+makarandh@users.noreply.github.com
License: UNKNOWN
Platform: UNKNOWN
Classifier: Programming Language :: Python :: 3
Classifier: License :: OSI Approved :: GNU General Public License v3 (GPLv3)
Classifier: Operating System :: OS Independent
